nuvla/__init__.py
nuvla/job_engine/__init__.py
nuvla/job_engine/connector/__init__.py
nuvla/job_engine/connector/coe_resources.py
nuvla/job_engine/connector/connector.py
nuvla/job_engine/connector/docker_compose.py
nuvla/job_engine/connector/docker_stack.py
nuvla/job_engine/connector/helm_driver.py
nuvla/job_engine/connector/k8s_driver.py
nuvla/job_engine/connector/kubernetes.py
nuvla/job_engine/connector/nuvlaedge_docker.py
nuvla/job_engine/connector/nuvlaedge_k8s.py
nuvla/job_engine/connector/registry.py
nuvla/job_engine/connector/utils.py
nuvla/job_engine/job/__init__.py
nuvla/job_engine/job/actions/__init__.py
nuvla/job_engine/job/actions/application_docker_compose_validate.py
nuvla/job_engine/job/actions/bulk_delete_deployment.py
nuvla/job_engine/job/actions/bulk_deployment_set_start.py
nuvla/job_engine/job/actions/bulk_deployment_set_stop.py
nuvla/job_engine/job/actions/bulk_deployment_set_update.py
nuvla/job_engine/job/actions/bulk_force_delete_deployment.py
nuvla/job_engine/job/actions/bulk_stop_deployment.py
nuvla/job_engine/job/actions/bulk_update_deployment.py
nuvla/job_engine/job/actions/bulk_update_nuvlabox.py
nuvla/job_engine/job/actions/cancel_children_jobs.py
nuvla/job_engine/job/actions/coe_resource_actions.py
nuvla/job_engine/job/actions/component_image_state.py
nuvla/job_engine/job/actions/credential_check.py
nuvla/job_engine/job/actions/dct_check.py
nuvla/job_engine/job/actions/deployment_log_fetch.py
nuvla/job_engine/job/actions/deployment_set_automatic_update.py
nuvla/job_engine/job/actions/deployment_set_delete.py
nuvla/job_engine/job/actions/deployment_set_force_delete.py
nuvla/job_engine/job/actions/deployment_start.py
nuvla/job_engine/job/actions/deployment_state.py
nuvla/job_engine/job/actions/deployment_stop.py
nuvla/job_engine/job/actions/deployment_update.py
nuvla/job_engine/job/actions/dummy_test_action.py
nuvla/job_engine/job/actions/handle_trial_end.py
nuvla/job_engine/job/actions/jobs_cleanup.py
nuvla_job_engine-5.1.4.dist-info/LICENSE
nuvla_job_engine-5.1.4.dist-info/METADATA
nuvla_job_engine-5.1.4.dist-info/WHEEL
nuvla_job_engine-5.1.4.dist-info/RECORD
