Metadata-Version: 2.3
Name: nuvla-job-engine
Version: 5.1.4
Summary: Nuvla Job Engine.
License: Apache-2.0
Author: SixSq SA
Author-email: support@sixsq.com
Maintainer: Ignacio Penas
Maintainer-email: nacho@sixsq.com
Requires-Python: >=3.11,<4.0
Classifier: Development Status :: 5 - Production/Stable
Classifier: Intended Audience :: Developers
Classifier: Intended Audience :: System Administrators
Classifier: License :: OSI Approved :: Apache Software License
Classifier: Operating System :: OS Independent
Classifier: Programming Language :: Python :: 3
Classifier: Programming Language :: Python :: 3.11
Classifier: Programming Language :: Python :: 3.12
Classifier: Programming Language :: Python :: 3.13
Classifier: Topic :: Software Development
Requires-Dist: docker (>=7.1.0,<8.0.0)
Requires-Dist: importlib-metadata (>=7.0.1,<8.0.0)
Requires-Dist: nuvla-api (>=4.2.1,<5.0.0)
Requires-Dist: packaging (>=23.2,<24.0)
Requires-Dist: pyyaml (>=6.0.1,<7.0.0)
Requires-Dist: statsd (>=4.0.1,<5.0.0)
Project-URL: Repository, https://github.com/nuvla/job-engine
